pyrave
