Metadata-Version: 1.1
Name: pyrave
Version: 1.0.3a0
Summary: Python wrapper flutterwave's rave API
Home-page: https://github.com/Olamyy/pyrave
Author: Olamilekan Wahab
Author-email: olamyy53@gmail.com
License: MIT
Download-URL: https://github.com/Olamyy/pyrave/archive/0.1.tar.gz
Keywords: rave,payment,pyrave
Platform: UNKNOWN
